osm/__init__.py
osm/parser.py
osm/road.py
osmRoad_nadfity-0.2.1a0.dist-info/LICENSE
osmRoad_nadfity-0.2.1a0.dist-info/METADATA
osmRoad_nadfity-0.2.1a0.dist-info/WHEEL
osmRoad_nadfity-0.2.1a0.dist-info/top_level.txt
osmRoad_nadfity-0.2.1a0.dist-info/RECORD
