Metadata-Version: 2.1
Name: osmRoad-nadfity
Version: 0.2.1a0
Summary: Parse OSM Data
Home-page: https://github.com/nadfity/osmRoad
Author: Muhammad Yasirroni
Author-email: muhammadyasirroni@gmail.com
Classifier: Programming Language :: Python :: 3
Classifier: License :: OSI Approved :: MIT License
Classifier: Operating System :: OS Independent
License-File: LICENSE
